spodcast/__init__.py
spodcast/__main__.py
spodcast/app.py
spodcast/config.py
spodcast/const.py
spodcast/feedgenerator.py
spodcast/podcast.py
spodcast/spodcast.py
spodcast/spotapi.py
spodcast/utils.py
spodcast-0.4.9.dist-info/LICENSE
spodcast-0.4.9.dist-info/METADATA
spodcast-0.4.9.dist-info/WHEEL
spodcast-0.4.9.dist-info/entry_points.txt
spodcast-0.4.9.dist-info/top_level.txt
spodcast-0.4.9.dist-info/RECORD
