Metadata-Version: 2.1
Name: spodcast
Version: 0.4.9
Summary: A caching Spotify podcast to RSS proxy.
Home-page: https://github.com/Yetangitu/spodcast.git
Author: yetangitu
Author-email: github-f@unternet.org
Project-URL: Bug Tracker, https://github.com/Yetangitu/spodcast/issues
Platform: any
Classifier: License :: OSI Approved :: GNU General Public License v3 (GPLv3)
Classifier: Programming Language :: Python :: 3.9
Classifier: Programming Language :: PHP
License-File: LICENSE
Requires-Dist: librespot (>=0.0.1)
Requires-Dist: ffmpeg-python
Requires-Dist: setuptools
